fastapi_h5/__init__.py
fastapi_h5/h5routes.py
fastapi_h5/h5types.py
fastapi_h5/utils.py
fastapi_h5-0.2.0.dist-info/licenses/LICENSE
fastapi_h5-0.2.0.dist-info/METADATA
fastapi_h5-0.2.0.dist-info/WHEEL
fastapi_h5-0.2.0.dist-info/top_level.txt
fastapi_h5-0.2.0.dist-info/RECORD
